Workbook

Sheet Dashboard
A1: Dashboard Executivo - Engenharia de Funil OSI | B1: Dashboard Executivo - Engenharia de Funil OSI | C1: Dashboard Executivo - Engenharia de Funil OSI | D1: Dashboard Executivo - Engenharia de Funil OSI | E1: Dashboard Executivo - Engenharia de Funil OSI | F1: Dashboard Executivo - Engenharia de Funil OSI | G1: Dashboard Executivo - Engenharia de Funil OSI | H1: Dashboard Executivo - Engenharia de Funil OSI | I1: Dashboard Executivo - Engenharia de Funil OSI | J1: Dashboard Executivo - Engenharia de Funil OSI
A3: KPI | B3: Valor | G3: Leitura rapida
A4: Ticket medio base | B4: =Premissas!B23 -> 135.41 | G4: Criativo valido | H4: CTR >= 1,5% e CPV <= R$ 1,39
A5: CPA maximo no ROAS alvo | B5: =Premissas!B23/Premissas!B18 -> 54.164 | G5: Meta economica | H5: ROAS alvo 2,5
A6: Gasto microteste | B6: =Modelo_ROAS!B4 -> 100 | G6: AOV aumenta CPA | H6: Bumps + upsell elevam teto de aquisicao
A7: Receita base projetada | B7: =Modelo_ROAS!H6 -> 3179.1913 | G7: Recuperacao | H7: Meta inicial 5% a 12% dos abandonos
A8: Lucro base apos ads | B8: =Modelo_ROAS!J6 -> 1893.0641 | G8: Primeira escala | H8: Duplicar gancho vencedor antes de ampliar publico
A10: Cenario | B10: Gasto | C10: Receita | D10: Lucro | E10: ROAS
A11: =Modelo_ROAS!A4 -> Microteste | B11: =Modelo_ROAS!B4 -> 100 | C11: =Modelo_ROAS!H4 -> 304.6725 | D11: =Modelo_ROAS!J4 -> 177.25198 | E11: =Modelo_ROAS!K4 -> 3.046725
A12: =Modelo_ROAS!A5 -> Conservador | B12: =Modelo_ROAS!B5 -> 500 | C12: =Modelo_ROAS!H5 -> 914.0175 | D12: =Modelo_ROAS!J5 -> 331.75593 | E12: =Modelo_ROAS!K5 -> 1.828035
A13: =Modelo_ROAS!A6 -> Base | B13: =Modelo_ROAS!B6 -> 1000 | C13: =Modelo_ROAS!H6 -> 3179.1913 | D13: =Modelo_ROAS!J6 -> 1893.0641 | E13: =Modelo_ROAS!K6 -> 3.1791913
A14: =Modelo_ROAS!A7 -> Agressivo | B14: =Modelo_ROAS!B7 -> 2500 | C14: =Modelo_ROAS!H7 -> 12771.301 | D14: =Modelo_ROAS!J7 -> 9121.884 | E14: =Modelo_ROAS!K7 -> 5.1085204
A15: =Modelo_ROAS!A8 -> Controle | B15: =Modelo_ROAS!B8 -> 1000 | C15: =Modelo_ROAS!H8 -> 3046.725 | D15: =Modelo_ROAS!J8 -> 1772.5198 | E15: =Modelo_ROAS!K8 -> 3.046725
A18: Cenario | B18: Receita | C18: Lucro | D18: ROAS
A19: =Modelo_ROAS!A4 -> Microteste | B19: =Modelo_ROAS!H4 -> 304.6725 | C19: =Modelo_ROAS!J4 -> 177.25198 | D19: =Modelo_ROAS!K4 -> 3.046725
A20: =Modelo_ROAS!A5 -> Conservador | B20: =Modelo_ROAS!H5 -> 914.0175 | C20: =Modelo_ROAS!J5 -> 331.75593 | D20: =Modelo_ROAS!K5 -> 1.828035
A21: =Modelo_ROAS!A6 -> Base | B21: =Modelo_ROAS!H6 -> 3179.1913 | C21: =Modelo_ROAS!J6 -> 1893.0641 | D21: =Modelo_ROAS!K6 -> 3.1791913
A22: =Modelo_ROAS!A7 -> Agressivo | B22: =Modelo_ROAS!H7 -> 12771.301 | C22: =Modelo_ROAS!J7 -> 9121.884 | D22: =Modelo_ROAS!K7 -> 5.1085204
A23: =Modelo_ROAS!A8 -> Controle | B23: =Modelo_ROAS!H8 -> 3046.725 | C23: =Modelo_ROAS!J8 -> 1772.5198 | D23: =Modelo_ROAS!K8 -> 3.046725

Sheet Premissas
A1: Premissas Editaveis - Otica Sem Improviso | B1: Premissas Editaveis - Otica Sem Improviso | C1: Premissas Editaveis - Otica Sem Improviso | D1: Premissas Editaveis - Otica Sem Improviso | E1: Premissas Editaveis - Otica Sem Improviso | F1: Premissas Editaveis - Otica Sem Improviso | G1: Premissas Editaveis - Otica Sem Improviso | H1: Premissas Editaveis - Otica Sem Improviso
A3: Oferta | B3: Valor | C3: Tipo | D3: Observacao
A4: Produto principal | B4: 97 | C4: preco | D4: Manual OSI + App
A5: Bump WhatsApp | B5: 27 | C5: preco | D5: Kit de respostas rapidas
A6: Bump Checklist | B6: 19 | C6: preco | D6: Checklist de 30 segundos
A7: Upsell Taty | B7: 197 | C7: preco | D7: Treinamento OSI na Pratica
A9: Take rate Bump WhatsApp | B9: 0.35 | C9: premissa | D9: Meta base: 25% a 40%
A10: Take rate Bump Checklist | B10: 0.28 | C10: premissa | D10: Meta base: 20% a 35%
A11: Conversao Upsell | B11: 0.12 | C11: premissa | D11: Meta base: 8% a 15%
A12: Taxa/encargos estimados | B12: 0.09 | C12: premissa | D12: Editar conforme taxa real da plataforma
A14: Orcamento por conjunto/dia | B14: 12.5 | C14: trafego | D14: ABO por 2 dias
A15: Dias de teste | B15: 2 | C15: trafego | D15: Janela inicial
A16: Numero de conjuntos | B16: 4 | C16: trafego | D16: Ajustar conforme teste
A17: CPV maximo | B17: 1.39 | C17: KPI | D17: Limite informado
... A21: Recuperacao carrinho | B21: 0.08 | C21: premissa | D21: Meta inicial: 5% a 12%
A23: Ticket medio calculado | B23: =B4+(B5*B9)+(B6*B10)+(B7*B11) -> 135.41 | C23: formula | D23: Principal + bumps + upsell

Sheet Modelo_ROAS
A1: Modelo de ROAS e Lucro por Cenario | B1: Modelo de ROAS e Lucro por Cenario | C1: Modelo de ROAS e Lucro por Cenario | D1: Modelo de ROAS e Lucro por Cenario | E1: Modelo de ROAS e Lucro por Cenario | F1: Modelo de ROAS e Lucro por Cenario | G1: Modelo de ROAS e Lucro por Cenario | H1: Modelo de ROAS e Lucro por Cenario | I1: Modelo de ROAS e Lucro por Cenario | J1: Modelo de ROAS e Lucro por Cenario | K1: Modelo de ROAS e Lucro por Cenario
A3: Cenario | B3: Gasto ads | C3: Cliques/visitas | D3: Compras diretas | E3: Compras recuperadas | F3: Compras totais | G3: Ticket medio | H3: Receita bruta | I3: Taxas estimadas | J3: Lucro apos ads | K3: ROAS
A4: Microteste | B4: =Premissas!B14*Premissas!B15*Premissas!B16 -> 100 | C4: =B4/1.2 -> 83.333333 | D4: =C4*Premissas!B20 -> 2.0833333 | E4: =D4*Premissas!B21 -> 0.16666667 | F4: =D4+E4 -> 2.25 | G4: =Premissas!B23 -> 135.41 | H4: =F4*G4 -> 304.6725 | I4: =H4*Premissas!B12 -> 27.420525 | J4: =H4-I4-B4 -> 177.25198 | K4: =H4/B4 -> 3.046725
A5: Conservador | B5: =500 -> 500 | C5: =B5/1.4 -> 357.14286 | D5: =C5*0.018 -> 6.4285714 | E5: =D5*0.05 -> 0.32142857 | F5: =D5+E5 -> 6.75 | G5: =Premissas!B23 -> 135.41 | H5: =F5*G5 -> 914.0175 | I5: =H5*Premissas!B12 -> 82.261575 | J5: =H5-I5-B5 -> 331.75593 | K5: =H5/B5 -> 1.828035
A6: Base | B6: =1000 -> 1000 | C6: =B6/1.15 -> 869.56522 | D6: =C6*0.025 -> 21.73913 | E6: =D6*0.08 -> 1.7391304 | F6: =D6+E6 -> 23.478261 | G6: =Premissas!B23 -> 135.41 | H6: =F6*G6 -> 3179.1913 | I6: =H6*Premissas!B12 -> 286.12722 | J6: =H6-I6-B6 -> 1893.0641 | K6: =H6/B6 -> 3.1791913
A7: Agressivo | B7: =2500 -> 2500 | C7: =B7/0.95 -> 2631.5789 | D7: =C7*0.032 -> 84.210526 | E7: =D7*0.12 -> 10.105263 | F7: =D7+E7 -> 94.315789 | G7: =Premissas!B23 -> 135.41 | H7: =F7*G7 -> 12771.301 | I7: =H7*Premissas!B12 -> 1149.4171 | J7: =H7-I7-B7 -> 9121.884 | K7: =H7/B7 -> 5.1085204
A8: Controle | B8: =1000 -> 1000 | C8: =B8/1.2 -> 833.33333 | D8: =C8*Premissas!B20 -> 20.833333 | E8: =D8*Premissas!B21 -> 1.6666667 | F8: =D8+E8 -> 22.5 | G8: =Premissas!B23 -> 135.41 | H8: =F8*G8 -> 3046.725 | I8: =H8*Premissas!B12 -> 274.20525 | J8: =H8-I8-B8 -> 1772.5198 | K8: =H8/B8 -> 3.046725

Sheet Teste_ABO
A1: Matriz de Teste ABO - 48h | B1: Matriz de Teste ABO - 48h | C1: Matriz de Teste ABO - 48h | D1: Matriz de Teste ABO - 48h | E1: Matriz de Teste ABO - 48h | F1: Matriz de Teste ABO - 48h | G1: Matriz de Teste ABO - 48h | H1: Matriz de Teste ABO - 48h | I1: Matriz de Teste ABO - 48h | J1: Matriz de Teste ABO - 48h
A3: Conjunto | B3: Angulo | C3: Orcamento/dia | D3: Dias | E3: Gasto | F3: CTR link | G3: CPV | H3: Sinais esperados | I3: Status | J3: Acao
A4: Adset 1 | B4: Improviso no balcao | C4: =Premissas!B14 -> 12.5 | D4: =Premissas!B15 -> 2 | E4: =C4*D4 -> 25 | F4: 0.018 | G4: 1.2 | H4: Cliques qualificados | I4: =IF(AND(F4>=Premissas!B19,G4<=Premissas!B17),"Validar","Ajustar/Cortar") -> Validar | J4: Manter e observar compra
A5: Adset 2 | B5: Cliente diz caro | C5: =Premissas!B14 -> 12.5 | D5: =Premissas!B15 -> 2 | E5: =C5*D5 -> 25 | F5: 0.016 | G5: 1.39 | H5: Checkout ou compra | I5: =IF(AND(F5>=Premissas!B19,G5<=Premissas!B17),"Validar","Ajustar/Cortar") -> Validar | J5: Manter se houver sinais
A6: Adset 3 | B6: WhatsApp parado | C6: =Premissas!B14 -> 12.5 | D6: =Premissas!B15 -> 2 | E6: =C6*D6 -> 25 | F6: 0.014 | G6: 1.55 | H6: Revisar promessa | I6: =IF(AND(F6>=Premissas!B19,G6<=Premissas!B17),"Validar","Ajustar/Cortar") -> Ajustar/Cortar | J6: Novo gancho ou pausar
A7: Adset 4 | B7: Explicacao de lentes | C7: =Premissas!B14 -> 12.5 | D7: =Premissas!B15 -> 2 | E7: =C7*D7 -> 25 | F7: 0.021 | G7: 1.05 | H7: Sinal forte | I7: =IF(AND(F7>=Premissas!B19,G7<=Premissas!B17),"Validar","Ajustar/Cortar") -> Validar | J7: Duplicar variacao
A8: Adset 5 | B8: Time sem padrao | C8: =Premissas!B14 -> 12.5 | D8: =Premissas!B15 -> 2 | E8: =C8*D8 -> 25 | F8: 0.012 | G8: 1.7 | H8: Pausar se sem evento | I8: =IF(AND(F8>=Premissas!B19,G8<=Premissas!B17),"Validar","Ajustar/Cortar") -> Ajustar/Cortar | J8: Pausar se nao houver sinal

Sheet Recuperacao
A1: Projecao de Recuperacao de Carrinho | B1: Projecao de Recuperacao de Carrinho | C1: Projecao de Recuperacao de Carrinho | D1: Projecao de Recuperacao de Carrinho | E1: Projecao de Recuperacao de Carrinho | F1: Projecao de Recuperacao de Carrinho | G1: Projecao de Recuperacao de Carrinho | H1: Projecao de Recuperacao de Carrinho
A3: Etapa | B3: Visitantes | C3: Checkouts | D3: Abandono | E3: Taxa recuperacao | F3: Vendas recuperadas | G3: Ticket medio | H3: Receita recuperada
A4: Microteste | B4: =Modelo_ROAS!C4 -> 83.333333 | C4: =B4*0.08 -> 6.6666667 | D4: =C4*0.7 -> 4.6666667 | E4: =Premissas!B21 -> 0.08 | F4: =D4*E4 -> 0.37333333 | G4: =Premissas!B23 -> 135.41 | H4: =F4*G4 -> 50.553067
A5: Conservador | B5: =Modelo_ROAS!C5 -> 357.14286 | C5: =B5*0.07 -> 25 | D5: =C5*0.75 -> 18.75 | E5: =0.05 -> 0.05 | F5: =D5*E5 -> 0.9375 | G5: =Premissas!B23 -> 135.41 | H5: =F5*G5 -> 126.94688
A6: Base | B6: =Modelo_ROAS!C6 -> 869.56522 | C6: =B6*0.09 -> 78.26087 | D6: =C6*0.7 -> 54.782609 | E6: =0.08 -> 0.08 | F6: =D6*E6 -> 4.3826087 | G6: =Premissas!B23 -> 135.41 | H6: =F6*G6 -> 593.44904
A7: Agressivo | B7: =Modelo_ROAS!C7 -> 2631.5789 | C7: =B7*0.11 -> 289.47368 | D7: =C7*0.65 -> 188.15789 | E7: =0.12 -> 0.12 | F7: =D7*E7 -> 22.578947 | G7: =Premissas!B23 -> 135.41 | H7: =F7*G7 -> 3057.4153
A8: Meta 30 dias | B8: =5000 -> 5000 | C8: =B8*0.1 -> 500 | D8: =C8*0.7 -> 350 | E8: =Premissas!B21 -> 0.08 | F8: =D8*E8 -> 28 | G8: =Premissas!B23 -> 135.41 | H8: =F8*G8 -> 3791.48
